django_midtrans/__init__.py
django_midtrans/apps.py
tests/__init__.py
tests/test_adapters.py
django_midtrans-0.0.1a0.dist-info/LICENSE
django_midtrans-0.0.1a0.dist-info/METADATA
django_midtrans-0.0.1a0.dist-info/WHEEL
django_midtrans-0.0.1a0.dist-info/top_level.txt
django_midtrans-0.0.1a0.dist-info/RECORD
